examples/__init__.py
examples/test_unittest.py
tests/__init__.py
tests/common.py
tests/test_expectations.py
tests/test_testclass.py
wooper/__init__.py
wooper/assertions.py
wooper/expect.py
wooper/general.py
wooper/rest.py
wooper/test_class.py
wooper/steps/__init__.py
wooper/steps/expect.py
wooper/steps/general.py
wooper/steps/given.py
wooper/steps/then.py
wooper/steps/when.py
wooper-0.4.4.dist-info/LICENSE
wooper-0.4.4.dist-info/METADATA
wooper-0.4.4.dist-info/WHEEL
wooper-0.4.4.dist-info/top_level.txt
wooper-0.4.4.dist-info/RECORD
