Metadata-Version: 2.1
Name: wooper
Version: 0.4.4
Summary: FrisbyJS-inspired REST API testing helpers and steps for 'behave' behavior-driven development testing library
Home-page: http://github.com/actionless/wooper
Author: Yauhen Kirylau
Author-email: actionless.loveless@gmail.com
License: GPL3
Platform: any
Classifier: Development Status :: 4 - Beta
Classifier: Environment :: Web Environment
Classifier: Intended Audience :: Developers
Classifier: Operating System :: OS Independent
Classifier: Programming Language :: Python
Classifier: Topic :: Software Development
Classifier: License :: OSI Approved :: GNU General Public License v3 (GPLv3)
Classifier: Programming Language :: Python :: 3.6
Classifier: Programming Language :: Python :: 3.7
Classifier: Programming Language :: Python :: 3.8
Requires-Dist: behave (<1.3,>=1.2.6)
Requires-Dist: requests (<3.0,>=2.20.0)
